musdk/__init__.py
musdk/client.py
musdk/main.py
musdk/user.py
musdk-0.0.7.dist-info/DESCRIPTION.rst
musdk-0.0.7.dist-info/METADATA
musdk-0.0.7.dist-info/RECORD
musdk-0.0.7.dist-info/WHEEL
musdk-0.0.7.dist-info/metadata.json
musdk-0.0.7.dist-info/top_level.txt
