Metadata-Version: 2.0
Name: musdk
Version: 0.0.7
Summary: ss-panel mu api sdk for python
Home-page: https://github.com/orvice/mu-py-sdk
Author: orvice
Author-email: orvice@orx.me
License: MIT
Platform: UNKNOWN
Classifier: Natural Language :: English
Classifier: Operating System :: MacOS :: MacOS X
Classifier: Operating System :: POSIX
Classifier: Operating System :: POSIX :: BSD
Classifier: Operating System :: POSIX :: Linux
Classifier: Operating System :: Microsoft :: Windows
Classifier: Programming Language :: Python
Classifier: Programming Language :: Python :: 2
Classifier: Programming Language :: Python :: 2.7
Classifier: Programming Language :: Python :: 3
Classifier: Programming Language :: Python :: 3.2
Classifier: Programming Language :: Python :: 3.3
Classifier: Programming Language :: Python :: 3.4
Classifier: Programming Language :: Python :: 3.5
Classifier: Programming Language :: Python :: Implementation :: CPython
Classifier: Programming Language :: Python :: Implementation :: PyPy
Requires-Dist: requests (>=2.5.0)
Requires-Dist: requests-toolbelt (>=0.5.1)
Requires-Dist: setuptools (>=0.7.0)
Requires-Dist: simplejson (>=3.1.0)
